Metadata-Version: 2.1
Name: tivan-custom-ser
Version: 0.1
Summary: Python JSON and XML serializer
Home-page: UNKNOWN
Author: tivan
Author-email: tenugo.v@gmail.com
License: MIT
Platform: UNKNOWN
